flexcalc/__init__.py
flexcalc/analyze.py
flexcalc/pipeline.py
flexcalc/process.py
flexcalc-1.0.0.dist-info/LICENSE.md
flexcalc-1.0.0.dist-info/METADATA
flexcalc-1.0.0.dist-info/WHEEL
flexcalc-1.0.0.dist-info/top_level.txt
flexcalc-1.0.0.dist-info/RECORD
