Metadata-Version: 2.1
Name: flexcalc
Version: 1.0.0
Summary: CT data pre- and post-processing tools, simulation of spectral data, and batch-processing of large number of datasets
Home-page: https://github.com/cicwi/flexcalc
Author: Alex Kostenko
License: GNU General Public License v3
License-File: LICENSE.md
Requires-Dist: numpy
Requires-Dist: tqdm
Requires-Dist: simpleitk
Requires-Dist: scipy
Requires-Dist: scikit-image
Requires-Dist: flexdata
Requires-Dist: flextomo
Provides-Extra: dev
Requires-Dist: sphinx; extra == "dev"
Requires-Dist: sphinx-rtd-theme; extra == "dev"
Requires-Dist: myst-parser; extra == "dev"
Provides-Extra: draw
Requires-Dist: networkx; extra == "draw"
Requires-Dist: pygraphviz; extra == "draw"
Provides-Extra: mesh
Requires-Dist: numpy-stl; extra == "mesh"
